satyrus/__init__.py
satyrus/__main__.py
satyrus/api/__init__.py
satyrus/api/api.py
satyrus/assets/__init__.py
satyrus/assets/banner.py
satyrus/assets/critical.py
satyrus/cli/__init__.py
satyrus/cli/api_cli.py
satyrus/cli/cli.py
satyrus/cli/help.py
satyrus/compiler/__init__.py
satyrus/compiler/compiler.py
satyrus/compiler/memory.py
satyrus/compiler/instructions/__init__.py
satyrus/compiler/instructions/def_array.py
satyrus/compiler/instructions/def_constant.py
satyrus/compiler/instructions/def_constraint.py
satyrus/compiler/instructions/instructions.py
satyrus/compiler/instructions/run_init.py
satyrus/compiler/instructions/run_script.py
satyrus/compiler/instructions/sys_config.py
satyrus/error/__init__.py
satyrus/parser/__init__.py
satyrus/parser/parser.py
satyrus/parser/legacy/__init__.py
satyrus/parser/legacy/legacy.py
satyrus/satlib/__init__.py
satyrus/satlib/main.py
satyrus/satlib/package.py
satyrus/satlib/performance.py
satyrus/satlib/posiform.py
satyrus/satlib/pythonshell.py
satyrus/satlib/source.py
satyrus/satlib/stack.py
satyrus/satyrus/__init__.py
satyrus/satyrus/satyrus.py
satyrus/symbols/__init__.py
satyrus/types/__init__.py
satyrus/types/array.py
satyrus/types/base.py
satyrus/types/expr.py
satyrus/types/number.py
satyrus/types/python.py
satyrus/types/string.py
satyrus/types/var.py
satyrus-3.0.7.data/data/satyrus_data/.sat-api
satyrus-3.0.7.data/data/satyrus_data/.satyrus
satyrus-3.0.7.data/data/satyrus_data/csv.py
satyrus-3.0.7.data/data/satyrus_data/dwave.py
satyrus-3.0.7.data/data/satyrus_data/gurobi.py
satyrus-3.0.7.data/data/satyrus_data/qubo.py
satyrus-3.0.7.data/scripts/satyrus
satyrus-3.0.7.dist-info/LICENSE
satyrus-3.0.7.dist-info/METADATA
satyrus-3.0.7.dist-info/WHEEL
satyrus-3.0.7.dist-info/entry_points.txt
satyrus-3.0.7.dist-info/top_level.txt
satyrus-3.0.7.dist-info/RECORD
